base/__init__.py
base/main.py
Nombres-1.2.dist-info/METADATA
Nombres-1.2.dist-info/WHEEL
Nombres-1.2.dist-info/top_level.txt
Nombres-1.2.dist-info/RECORD
