Metadata-Version: 2.1
Name: Nombres
Version: 1.2
Summary: Muestra 100 nombres de hombre y 10 nombres de mujer 
Home-page: https://github.com/itzelfd98
Author: ItzelFranco
Author-email: itzel_fd1@tesch.edu.mx
License: GNU GPL
Requires-Dist: pandas
